{
  "Additions": [
    "CA42841L1085,A3DE86,HI-VIEW RESOURCES INC.,Aktien International,Aktien International,,",
    "CA82888R1055,A3CN6D,SIMPLY BETTER BRANDS O.N.,Aktien International,Aktien International,,",
    "US38045R2067,A2AE3E,GOL L.A.I.PFD ADR 1/2,Aktien International,Aktien International,,",
    "US7731221062,A3CY7P,\"ROCKET LAB USA A DL-, 0001\",Aktien USA,Aktien USA Select,,"
  ],
  "Modifications": [],
  "Deletions": [
    "CA0211551068,A40M0J,ALSET AI VENTURES INC.,Aktien International,Aktien International,,",
    "DE000A2LQ710,A2LQ71,LODGYSLIFE AG INH O.N.,Aktien Deutschland,Aktien Sonstige,,",
    "SE0015556873,A2QRYM,CHEFFELO AB,Aktien Europa,Aktien Europa Select,,",
    "CH1386220409,A40VTK,\"SUNRISE COMMUNIC.NA.SF-, 1\",Aktien Europa,Aktien Europa Select,,",
    "CH0045825517,A0YCD3,FUNDAMENTA R.E.NAM. SF 6,Aktien Europa,Aktien Europa Select,,",
    "CA89778A1003,A417U9,TRUBAR INC.,Aktien International,Aktien International,,",
    "US68247Q2012,A40ZAX,111 INC.  ADR/20 CL.A,Aktien International,Aktien International,,",
    "CH0024736404,A0KFH3,EDISUN POWER E.NAM. SF30,Aktien Europa,Aktien Europa Select,,",
    "CH0451123589,A2QN5W,\"SWISSNET AG       SF -, 10\",Aktien Europa,Aktien Europa Select,,",
    "CA42841L2075,A419HN,HI-VIEW RESOURCES INC.,Aktien International,Aktien International,,",
    "SE0021020716,A3E19M,AAC CLYDE SPACE AB   O.N.,Aktien Europa,Aktien Europa Select,,",
    "SE0024171458,A4149T,ASKER HEALTHCARE  O.N.,Aktien Europa,Aktien Europa Select,,",
    "CH1169360919,A3DRSU,ACCELLERON INDS NAM.SF-01,Aktien Europa,Aktien Europa Select,,",
    "CH0013396012,A0MPG1,\"SKAN GROUP AG     SF 0, 01\",Aktien Europa,Aktien Europa Select,,",
    "FI4000517966,A416C9,GRK INFRA OYJ     EO 1,Aktien Europa,Aktien Europa Select,,",
    "CH0003583256,896040,HIGHL.EVENT A.ENT.INH.SF1,Aktien Europa,Aktien Europa Select,,",
    "CH0524026959,A2P2BK,\"CHAM SWISS PROP.  SF -, 03\",Aktien Europa,Aktien Europa Select,,",
    "CH1330780979,A40BDL,\"CURATIS HOLDING AG SF-, 10\",Aktien Europa,Aktien Europa Select,,",
    "US7731211089,A419CG,ROCKET LAB CORP. O.N.,Aktien USA,Aktien USA Select,,",
    "CH1335392721,A407X6,GALDERMA GRP AG,Aktien Europa,Aktien Europa Select,,"
  ],
  "Summary": {
    "Additions": 4,
    "Modifications": 0,
    "Deletions": 20
  }
}
