{
  "Additions": [
    "DE000LS9KTA4,LS9KTA,Wachstum mit Risikostreuung,sonstige Anlagezertifikate,wikifolio-Zertifikate ohne Hebelprodukte",
    "DE000LS9MLC3,LS9MLC,Wachstum mit deutscher Stärke,sonstige Anlagezertifikate,wikifolio-Zertifikate ohne Hebelprodukte",
    "DE000LS9UFV8,LS9UFV,MasteroftheUniverse,sonstige Anlagezertifikate,wikifolio-Zertifikate mit Hebelprodukten",
    "DE000LS9TNL5,LS9TNL,AGRAR Weizen Mais Soja mit Hebel,sonstige Anlagezertifikate,wikifolio-Zertifikate mit Hebelprodukten"
  ],
  "Modifications": [],
  "Deletions": [],
  "Summary": {
    "Additions": 4,
    "Modifications": 0,
    "Deletions": 0
  }
}
